pyshexc/ShExC.py
pyshexc/__init__.py
pyshexc/parser/ShExDoc.interp
pyshexc/parser/ShExDoc.tokens
pyshexc/parser/ShExDocLexer.interp
pyshexc/parser/ShExDocLexer.py
pyshexc/parser/ShExDocLexer.tokens
pyshexc/parser/ShExDocParser.py
pyshexc/parser/ShExDocVisitor.py
pyshexc/parser/__init__.py
pyshexc/parser_impl/__init__.py
pyshexc/parser_impl/generate_shexj.py
pyshexc/parser_impl/parser_context.py
pyshexc/parser_impl/shex_annotations_and_semacts_parser.py
pyshexc/parser_impl/shex_doc_parser.py
pyshexc/parser_impl/shex_node_expression_parser.py
pyshexc/parser_impl/shex_oneofshape_parser.py
pyshexc/parser_impl/shex_shape_definition_parser.py
pyshexc/parser_impl/shex_shape_expression_parser.py
pyshexc/rdflib/__init__.py
pyshexc/rdflib/contextcache.py
PyShExC-0.9.1.dist-info/AUTHORS
PyShExC-0.9.1.dist-info/LICENSE
PyShExC-0.9.1.dist-info/METADATA
PyShExC-0.9.1.dist-info/WHEEL
PyShExC-0.9.1.dist-info/top_level.txt
PyShExC-0.9.1.dist-info/RECORD
